{"4002": {"room": "G2-12", "condition": "Dirty", "status": "Offer Out", "libraries": []}, "4021": {"room": "G2-12", "condition": "Clean", "status": "keep", "libraries": []}, "4022": {"room": "G2-12", "condition": "Dirty", "status": "Dispose", "libraries": []}, "4023": {"room": "G2-12", "condition": "Clean", "status": "keep", "libraries": []}, "4029": {"room": "G2-12", "condition": "Dirty", "status": "Keep", "libraries": []}, "4048": {"room": "G2-12", "condition": "Clean", "status": "Keep", "libraries": []}, "4055": {"room": "G2-12", "condition": "Dirty", "status": "Keep", "libraries": []}, "4007": {"room": "G1-42", "condition": "Clean", "status": "Offer Out", "libraries": []}, "4015": {"room": "G1-42", "condition": "Clean", "status": "Dispose", "libraries": []}, "4019": {"room": "G1-42", "condition": "Clean", "status": "Dispose", "libraries": []}, "4024": {"room": "G1-42", "condition": "Clean", "status": "Offer Out", "libraries": []}, "4008": {"room": "B1-06", "condition": "Dirty", "status": "Dispose", "libraries": []}, "4011": {"room": "B1-06", "condition": "Clean", "status": "Dispose", "libraries": []}, "4026": {"room": "B1-06", "condition": "Dirty", "status": "Dispose", "libraries": []}, "4046": {"room": "B1-06", "condition": "Dirty", "status": "Offer Out", "libraries": []}, "4049": {"room": "B1-06", "condition": "Clean", "status": "Dispose", "libraries": []}, "4009": {"room": "G1-32", "condition": "Clean", "status": "Keep", "libraries": []}, "4012": {"room": "G1-32", "condition": "Clean", "status": "Offer Out", "libraries": []}, "4014": {"room": "G1-32", "condition": "Clean", "status": "Keep", "libraries": []}, "4025": {"room": "G1-32", "condition": "Dirty", "status": "Dispose", "libraries": []}, "4027": {"room": "G1-32", "condition": "Clean", "status": "Keep", "libraries": []}, "4028": {"room": "G1-32", "condition": "Dirty", "status": "Offer Out", "libraries": []}, "4038": {"room": "G1-32", "condition": "Clean", "status": "Dispose", "libraries": []}, "4039": {"room": "G1-32", "condition": "Dirty", "status": "Keep", "libraries": []}, "4040": {"room": "G1-32", "condition": "Clean", "status": "Keep", "libraries": []}, "4051": {"room": "G1-32", "condition": "Clean", "status": "Dispose", "libraries": []}, "4052": {"room": "G1-32", "condition": "Clean", "status": "Dispose", "libraries": []}, "4057": {"room": "G1-32", "condition": "Dirty", "status": "Dispose", "libraries": []}, "4018": {"room": "G1-33", "condition": "Dirty", "status": "Dispose", "libraries": []}, "4031": {"room": "G1-33", "condition": "Clean", "status": "Dispose", "libraries": []}, "4032": {"room": "G1-33", "condition": "Dirty", "status": "Dispose", "libraries": []}, "4036": {"room": "G1-33", "condition": "Dirty", "status": "Dispose", "libraries": []}, "4042": {"room": "G1-33", "condition": "Dirty", "status": "Dispose", "libraries": []}, "4054": {"room": "G1-33", "condition": "Clean", "status": "Keep", "libraries": []}, "4069": {"room": "G1-33", "condition": "Clean", "status": "Keep", "libraries": []}, "4070": {"room": "G1-33", "condition": "Dirty", "status": "Keep", "libraries": []}, "4033": {"room": "G2-18", "condition": "Dirty", "status": "Dispose", "libraries": []}, "4050": {"room": "G2-18", "condition": "Dirty", "status": "Keep", "libraries": []}, "4058": {"room": "G1-28", "condition": "Dirty", "status": "Dispose", "libraries": []}, "4060": {"room": "B1-05", "condition": "Clean", "status": "Dispose", "libraries": []}, "4061": {"room": "B1-05", "condition": "Clean", "status": "Dispose", "libraries": []}, "4063": {"room": "B1-05", "condition": "Clean", "status": "Dispose", "libraries": []}, "4064": {"room": "B1-05", "condition": "Clean", "status": "Dispose", "libraries": []}, "4068": {"room": "B1-09", "condition": "Clean", "status": "Offer Out", "libraries": []}}